<annotation>
	<folder>resources</folder>
	<filename>IMG_4320_wb.jpg</filename>
	<path>D:/projects/CornClassifier/resources/IMG_4320_wb.jpg</path>
	<source>
		<database>Unknown</database>
	</source>
	<size>
		<width>3648</width>
		<height>2736</height>
		<depth>3</depth>
	</size>
	<segmented>0</segmented>
	<object>
		<name>buckwheat</name>
		<pose>Unspecified</pose>
		<truncated>0</truncated>
		<difficult>0</difficult>
		<bndbox>
			<xmin>614</xmin>
			<ymin>162</ymin>
			<xmax>642</xmax>
			<ymax>210</ymax>
		</bndbox>
	</object>
	<object>
		<name>buckwheat</name>
		<pose>Unspecified</pose>
		<truncated>0</truncated>
		<difficult>0</difficult>
		<bndbox>
			<xmin>455</xmin>
			<ymin>423</ymin>
			<xmax>489</xmax>
			<ymax>471</ymax>
		</bndbox>
	</object>
	<object>
		<name>buckwheat</name>
		<pose>Unspecified</pose>
		<truncated>0</truncated>
		<difficult>0</difficult>
		<bndbox>
			<xmin>536</xmin>
			<ymin>192</ymin>
			<xmax>581</xmax>
			<ymax>242</ymax>
		</bndbox>
	</object>
	<object>
		<name>buckwheat</name>
		<pose>Unspecified</pose>
		<truncated>0</truncated>
		<difficult>0</difficult>
		<bndbox>
			<xmin>248</xmin>
			<ymin>279</ymin>
			<xmax>308</xmax>
			<ymax>320</ymax>
		</bndbox>
	</object>
	<object>
		<name>buckwheat</name>
		<pose>Unspecified</pose>
		<truncated>0</truncated>
		<difficult>0</difficult>
		<bndbox>
			<xmin>465</xmin>
			<ymin>306</ymin>
			<xmax>511</xmax>
			<ymax>363</ymax>
		</bndbox>
	</object>
	<object>
		<name>buckwheat</name>
		<pose>Unspecified</pose>
		<truncated>0</truncated>
		<difficult>0</difficult>
		<bndbox>
			<xmin>407</xmin>
			<ymin>143</ymin>
			<xmax>454</xmax>
			<ymax>203</ymax>
		</bndbox>
	</object>
</annotation>