<annotation>
	<folder>resources</folder>
	<filename>IMG_4319_wb.jpg</filename>
	<path>D:/projects/CornClassifier/resources/IMG_4319_wb.jpg</path>
	<source>
		<database>Unknown</database>
	</source>
	<size>
		<width>3648</width>
		<height>2736</height>
		<depth>3</depth>
	</size>
	<segmented>0</segmented>
	<object>
		<name>other</name>
		<pose>Unspecified</pose>
		<truncated>0</truncated>
		<difficult>0</difficult>
		<bndbox>
			<xmin>505</xmin>
			<ymin>31</ymin>
			<xmax>525</xmax>
			<ymax>67</ymax>
		</bndbox>
	</object>
	<object>
		<name>dill</name>
		<pose>Unspecified</pose>
		<truncated>0</truncated>
		<difficult>0</difficult>
		<bndbox>
			<xmin>235</xmin>
			<ymin>477</ymin>
			<xmax>326</xmax>
			<ymax>500</ymax>
		</bndbox>
	</object>
	<object>
		<name>buckwheat</name>
		<pose>Unspecified</pose>
		<truncated>0</truncated>
		<difficult>0</difficult>
		<bndbox>
			<xmin>596</xmin>
			<ymin>434</ymin>
			<xmax>639</xmax>
			<ymax>488</ymax>
		</bndbox>
	</object>
	<object>
		<name>buckwheat</name>
		<pose>Unspecified</pose>
		<truncated>0</truncated>
		<difficult>0</difficult>
		<bndbox>
			<xmin>15</xmin>
			<ymin>514</ymin>
			<xmax>53</xmax>
			<ymax>577</ymax>
		</bndbox>
	</object>
	<object>
		<name>buckwheat</name>
		<pose>Unspecified</pose>
		<truncated>0</truncated>
		<difficult>0</difficult>
		<bndbox>
			<xmin>335</xmin>
			<ymin>389</ymin>
			<xmax>383</xmax>
			<ymax>438</ymax>
		</bndbox>
	</object>
	<object>
		<name>mais</name>
		<pose>Unspecified</pose>
		<truncated>0</truncated>
		<difficult>0</difficult>
		<bndbox>
			<xmin>259</xmin>
			<ymin>514</ymin>
			<xmax>322</xmax>
			<ymax>615</ymax>
		</bndbox>
	</object>
	<object>
		<name>mais</name>
		<pose>Unspecified</pose>
		<truncated>0</truncated>
		<difficult>0</difficult>
		<bndbox>
			<xmin>362</xmin>
			<ymin>73</ymin>
			<xmax>426</xmax>
			<ymax>172</ymax>
		</bndbox>
	</object>
	<object>
		<name>mais</name>
		<pose>Unspecified</pose>
		<truncated>0</truncated>
		<difficult>0</difficult>
		<bndbox>
			<xmin>93</xmin>
			<ymin>230</ymin>
			<xmax>168</xmax>
			<ymax>316</ymax>
		</bndbox>
	</object>
	<object>
		<name>mais</name>
		<pose>Unspecified</pose>
		<truncated>0</truncated>
		<difficult>0</difficult>
		<bndbox>
			<xmin>597</xmin>
			<ymin>266</ymin>
			<xmax>642</xmax>
			<ymax>382</ymax>
		</bndbox>
	</object>
	<object>
		<name>mais</name>
		<pose>Unspecified</pose>
		<truncated>0</truncated>
		<difficult>0</difficult>
		<bndbox>
			<xmin>-1</xmin>
			<ymin>366</ymin>
			<xmax>70</xmax>
			<ymax>456</ymax>
		</bndbox>
	</object>
</annotation>