<annotation>
	<folder>resources</folder>
	<filename>IMG_4323_wb17.jpg</filename>
	<path>IMG_4323_wb17.jpg</path>
	<source>
		<database>Unknown</database>
	</source>
	<size>
		<width>640</width>
		<height>640</height>
		<depth>3</depth>
	</size>
	<segmented>0</segmented>
	<object>
		<name>buckwheat</name>
		<pose>Unspecified</pose>
		<truncated>0</truncated>
		<difficult>0</difficult>
		<bndbox>
			<xmin>75</xmin>
			<ymin>535</ymin>
			<xmax>119</xmax>
			<ymax>599</ymax>
		</bndbox>
	</object>
	<object>
		<name>buckwheat</name>
		<pose>Unspecified</pose>
		<truncated>0</truncated>
		<difficult>0</difficult>
		<bndbox>
			<xmin>155</xmin>
			<ymin>255</ymin>
			<xmax>211</xmax>
			<ymax>315</ymax>
		</bndbox>
	</object>
	<object>
		<name>mais</name>
		<pose>Unspecified</pose>
		<truncated>0</truncated>
		<difficult>0</difficult>
		<bndbox>
			<xmin>141</xmin>
			<ymin>369</ymin>
			<xmax>217</xmax>
			<ymax>462</ymax>
		</bndbox>
	</object>
	<object>
		<name>mais</name>
		<pose>Unspecified</pose>
		<truncated>0</truncated>
		<difficult>0</difficult>
		<bndbox>
			<xmin>617</xmin>
			<ymin>90</ymin>
			<xmax>640</xmax>
			<ymax>193</ymax>
		</bndbox>
	</object>
	<object>
		<name>mais</name>
		<pose>Unspecified</pose>
		<truncated>0</truncated>
		<difficult>0</difficult>
		<bndbox>
			<xmin>563</xmin>
			<ymin>323</ymin>
			<xmax>640</xmax>
			<ymax>404</ymax>
		</bndbox>
	</object>
</annotation>